openlist/__init__.py
openlist/context.py
openlist/data_types.py
openlist/exceptions.py
openlist/utils.py
openlist/core/__init__.py
openlist/core/admin.py
openlist/core/authentication.py
openlist/core/base.py
openlist/core/file.py
openlist-0.1.1b2.dist-info/licenses/LICENSE
openlist-0.1.1b2.dist-info/METADATA
openlist-0.1.1b2.dist-info/WHEEL
openlist-0.1.1b2.dist-info/top_level.txt
openlist-0.1.1b2.dist-info/RECORD
