Metadata-Version: 2.4
Name: openlist
Version: 0.1.1b2
Summary: A Python client for OpenList API
Author-email: HisAtri <sato@xms.mx>
Project-URL: Homepage, https://github.com/HisAtri/openlistapi
Classifier: Programming Language :: Python :: 3
Classifier: License :: OSI Approved :: MIT License
Classifier: Operating System :: OS Independent
Requires-Python: >=3.10
License-File: LICENSE
Requires-Dist: fsspec>=2025.10.0
Requires-Dist: httpx>=0.28.1
Requires-Dist: pydantic>=2.12.5
Requires-Dist: pyjwt>=2.10.1
Requires-Dist: pyotp>=2.9.0
Dynamic: license-file
